_drgn.cpython-38-x86_64-linux-gnu.so
_drgn.pyi
_drgn_util/__init__.py
_drgn_util/elf.py
_drgn_util/platform.py
_drgn_util/plugins.py
drgn/__init__.py
drgn/__main__.py
drgn/cli.py
drgn/py.typed
drgn/helpers/__init__.py
drgn/helpers/common/__init__.py
drgn/helpers/common/format.py
drgn/helpers/common/memory.py
drgn/helpers/common/prog.py
drgn/helpers/common/stack.py
drgn/helpers/common/type.py
drgn/helpers/experimental/__init__.py
drgn/helpers/experimental/kmodify.py
drgn/helpers/linux/__init__.py
drgn/helpers/linux/bitmap.py
drgn/helpers/linux/bitops.py
drgn/helpers/linux/block.py
drgn/helpers/linux/boot.py
drgn/helpers/linux/bpf.py
drgn/helpers/linux/cgroup.py
drgn/helpers/linux/cpumask.py
drgn/helpers/linux/device.py
drgn/helpers/linux/fs.py
drgn/helpers/linux/idr.py
drgn/helpers/linux/kallsyms.py
drgn/helpers/linux/kconfig.py
drgn/helpers/linux/kernfs.py
drgn/helpers/linux/kthread.py
drgn/helpers/linux/list.py
drgn/helpers/linux/list_nulls.py
drgn/helpers/linux/llist.py
drgn/helpers/linux/mapletree.py
drgn/helpers/linux/mm.py
drgn/helpers/linux/module.py
drgn/helpers/linux/net.py
drgn/helpers/linux/nodemask.py
drgn/helpers/linux/percpu.py
drgn/helpers/linux/pid.py
drgn/helpers/linux/plist.py
drgn/helpers/linux/printk.py
drgn/helpers/linux/radixtree.py
drgn/helpers/linux/rbtree.py
drgn/helpers/linux/sched.py
drgn/helpers/linux/slab.py
drgn/helpers/linux/stackdepot.py
drgn/helpers/linux/tc.py
drgn/helpers/linux/tcp.py
drgn/helpers/linux/timekeeping.py
drgn/helpers/linux/user.py
drgn/helpers/linux/wait.py
drgn/helpers/linux/xarray.py
drgn/internal/__init__.py
drgn/internal/repl.py
drgn/internal/rlcompleter.py
drgn/internal/sudohelper.py
drgn/internal/version.py
drgn.libs/libaddrxlat-7de263f3.so.3.1.4
drgn.libs/libbz2-a273e504.so.1.0.6
drgn.libs/libcom_err-2abe824b.so.2.1
drgn.libs/libcrypt-a115dc8d.so.1
drgn.libs/libcrypto-d3570994.so.1.0.2k
drgn.libs/libcurl-34c6b10f.so.4.3.0
drgn-0.0.32.dist-info/COPYING
drgn-0.0.32.dist-info/METADATA
drgn-0.0.32.dist-info/WHEEL
drgn-0.0.32.dist-info/entry_points.txt
drgn-0.0.32.dist-info/top_level.txt
drgn-0.0.32.dist-info/RECORD
