Metadata-Version: 2.1
Name: drgn
Version: 0.0.32
Summary: Programmable debugger
Home-page: https://github.com/osandov/drgn
Author: Omar Sandoval
Author-email: osandov@osandov.com
License: LGPL-2.1-or-later
Project-URL: Bug Tracker, https://github.com/osandov/drgn/issues
Project-URL: Documentation, https://drgn.readthedocs.io
Classifier: Development Status :: 5 - Production/Stable
Classifier: Environment :: Console
Classifier: Intended Audience :: Developers
Classifier: License :: OSI Approved :: GNU Lesser General Public License v2 or later (LGPLv2+)
Classifier: Operating System :: POSIX :: Linux
Classifier: Programming Language :: Python :: 3
Classifier: Topic :: Software Development :: Debuggers
Classifier: Topic :: System :: Operating System Kernels :: Linux
Requires-Python: >=3.6
License-File: COPYING
Requires-Dist: setuptools ; python_version < "3.8"
